asa_hmi_api-0.1.5.dist-info/METADATA
asa_hmi_api-0.1.5.dist-info/RECORD
asa_hmi_api-0.1.5.dist-info/WHEEL
asa_hmi_api-0.1.5.dist-info/top_level.txt
asahmi/__init__.py
asahmi/data_to_byte.py
asahmi/decoder.py
asahmi/hmi_handler.py
asahmi/hmi_handler_6w485.py
asahmi/hmi_handler_serial.py
asahmi/type.py
asahmi/util.py
asahmi/pac/__init__.py
asahmi/pac/decoder.py
asahmi/pac/general.py
asahmi/pac/hmi.py
asahmi/pac/packet.py
asahmi/pac/util.py
